BBLCalculator/__init__.py
BBLCalculator/bblcalculator.py
BBLCalculator-0.0.1.dist-info/LICENSE.txt
BBLCalculator-0.0.1.dist-info/METADATA
BBLCalculator-0.0.1.dist-info/WHEEL
BBLCalculator-0.0.1.dist-info/top_level.txt
BBLCalculator-0.0.1.dist-info/RECORD
