Metadata-Version: 2.1
Name: BBLCalculator
Version: 0.0.1
Summary: BBLCalculator
Author: BBL Group(Aman)
Author-email: thebblcodingroup@gmail.com
Keywords: arithmetic,math,mathematics,python tutorial,avi upadhyay
Classifier: Development Status :: 1 - Planning
Classifier: Intended Audience :: Developers
Classifier: Programming Language :: Python :: 3
Classifier: Operating System :: Unix
Classifier: Operating System :: MacOS :: MacOS X
Classifier: Operating System :: Microsoft :: Windows
License-File: LICENSE.txt
